bay_lang/__init__.py
bay_lang-0.0.1.data/scripts/bay-lang
bay_lang-0.0.1.dist-info/LICENSE
bay_lang-0.0.1.dist-info/METADATA
bay_lang-0.0.1.dist-info/WHEEL
bay_lang-0.0.1.dist-info/top_level.txt
bay_lang-0.0.1.dist-info/RECORD
